{
    "Ar36": {
        "error": 0.00035272625561426026, 
        "fit": "Linear", 
        "value": 0.013052311057052351
    }, 
    "Ar37": {
        "error": 0.00563269241966382, 
        "fit": "linear", 
        "value": 1.5982637787902891
    }, 
    "Ar38": {
        "error": 0.012467735018781251, 
        "fit": "linear", 
        "value": 6.366060198973325
    }, 
    "Ar39": {
        "error": 0.049196556647732724, 
        "fit": "Linear", 
        "value": 489.67308925370617
    }, 
    "Ar40": {
        "error": 0.1003709776695953, 
        "fit": "Linear", 
        "value": 1955.1647597579658
    }, 
    "Ar41": {
        "error": 0.0049314927459121775, 
        "fit": "Average", 
        "value": 0.1533909395065803
    }
}