{
    "Ar36": {
        "error": 0.00028683348789412355, 
        "fit": "Linear", 
        "value": 0.01242049373122861
    }, 
    "Ar37": {
        "error": 0.005313782134649573, 
        "fit": "linear", 
        "value": 0.9180076137811851
    }, 
    "Ar38": {
        "error": 0.010441999258340348, 
        "fit": "linear", 
        "value": 4.145392448869446
    }, 
    "Ar39": {
        "error": 0.04029661566254381, 
        "fit": "Linear", 
        "value": 315.6910434087016
    }, 
    "Ar40": {
        "error": 0.0689920076986656, 
        "fit": "Linear", 
        "value": 1265.5289823929716
    }, 
    "Ar41": {
        "error": 0.00482087876207583, 
        "fit": "Average", 
        "value": 0.12437345874621948
    }
}