{
    "AX": {
        "error": 0.012256341173813474, 
        "filter_outliers_dict": {
            "filter_outliers": true, 
            "iterations": 1, 
            "std_devs": 2
        }, 
        "fit": "average", 
        "value": -1.5331207498437351
    }, 
    "H1": {
        "error": 0.011431447698563468, 
        "filter_outliers_dict": {
            "filter_outliers": true, 
            "iterations": 1, 
            "std_devs": 2
        }, 
        "fit": "average", 
        "value": 0.04753433331879768
    }, 
    "H2": {
        "error": 0.01247373628626705, 
        "filter_outliers_dict": {
            "filter_outliers": true, 
            "iterations": 1, 
            "std_devs": 2
        }, 
        "fit": "average", 
        "value": -0.1619541714379227
    }, 
    "L1": {
        "error": 0.012208160253466679, 
        "filter_outliers_dict": {
            "filter_outliers": true, 
            "iterations": 1, 
            "std_devs": 2
        }, 
        "fit": "average", 
        "value": -0.05212974130983096
    }, 
    "L2(CDD)": {
        "error": 0.0, 
        "filter_outliers_dict": {
            "filter_outliers": true, 
            "iterations": 1, 
            "std_devs": 2
        }, 
        "fit": "average", 
        "value": 0.0
    }
}